{
  "id": "checkpoint_1748463171925_7zo45rkkb",
  "name": "Auto-checkpoint 10:12:51 PM",
  "timestamp": "2025-05-28T20:13:01.531Z",
  "description": "Automatic checkpoint after 3 changes:\nadd: .qapt-coder\\checkpoints\\checkpoint_1748463157401_ivazigdkg.metadata.json\nunlink: .qapt-coder\\checkpoints\\checkpoint_1748462721937_udr1eat55.zip\nunlink: .qapt-coder\\checkpoints\\checkpoint_1748462721937_udr1eat55.metadata.json",
  "filePath": "c:\\Users\\anwar\\Documents\\qapt\\.qapt-coder\\checkpoints\\checkpoint_1748463171925_7zo45rkkb.zip",
  "fileCount": 526,
  "size": 695125,
  "changes": []
}